unfuncaptcha_bio/__init__.py
unfuncaptcha_bio/event.py
unfuncaptcha_bio/points.py
unfuncaptcha_bio/bio/kbio.py
unfuncaptcha_bio/bio/mbio.py
unfuncaptcha_bio/bio/tbio.py
unfuncaptcha_bio-1.0.1.dist-info/LICENSE
unfuncaptcha_bio-1.0.1.dist-info/METADATA
unfuncaptcha_bio-1.0.1.dist-info/WHEEL
unfuncaptcha_bio-1.0.1.dist-info/top_level.txt
unfuncaptcha_bio-1.0.1.dist-info/RECORD
