Metadata-Version: 2.1
Name: unfuncaptcha_bio
Version: 1.0.1
Summary: Generate mouse, touch, and keyboard motions for Arkose Labs Funcaptcha
Author-email: bc <no@dont.email.me>
Project-URL: Homepage, https://github.com/unfuncaptcha/bio
Project-URL: Issues, https://github.com/unfuncaptcha/bio/issues
Classifier: Programming Language :: Python :: 3
Classifier: License :: OSI Approved :: MIT License
Classifier: Operating System :: OS Independent
Requires-Python: >=3.8
License-File: LICENSE
